odoo/addons/product_fao_fishing/README.rst
odoo/addons/product_fao_fishing/__init__.py
odoo/addons/product_fao_fishing/__manifest__.py
odoo/addons/product_fao_fishing/data/product_fao_fishing_data.xml
odoo/addons/product_fao_fishing/data/product_fao_fishing_techique_data.xml
odoo/addons/product_fao_fishing/i18n/.empty
odoo/addons/product_fao_fishing/i18n/es.po
odoo/addons/product_fao_fishing/i18n/product_fao_fishing.pot
odoo/addons/product_fao_fishing/i18n/pt_BR.po
odoo/addons/product_fao_fishing/migrations/12.0.1.0.0/post-migration.py
odoo/addons/product_fao_fishing/models/__init__.py
odoo/addons/product_fao_fishing/models/product_attribute.py
odoo/addons/product_fao_fishing/models/product_fao_fishing_technique.py
odoo/addons/product_fao_fishing/models/product_template.py
odoo/addons/product_fao_fishing/readme/CONFIGURE.rst
odoo/addons/product_fao_fishing/readme/CONTRIBUTORS.rst
odoo/addons/product_fao_fishing/readme/DESCRIPTION.rst
odoo/addons/product_fao_fishing/readme/USAGE.rst
odoo/addons/product_fao_fishing/security/ir.model.access.csv
odoo/addons/product_fao_fishing/static/description/icon.png
odoo/addons/product_fao_fishing/static/description/index.html
odoo/addons/product_fao_fishing/tests/__init__.py
odoo/addons/product_fao_fishing/tests/test_product_fao_fishing.py
odoo/addons/product_fao_fishing/views/product_attribute_views.xml
odoo/addons/product_fao_fishing/views/product_fao_techinique_views.xml
odoo/addons/product_fao_fishing/views/product_template_views.xml
odoo12_addon_product_fao_fishing-12.0.1.0.1.dist-info/METADATA
odoo12_addon_product_fao_fishing-12.0.1.0.1.dist-info/WHEEL
odoo12_addon_product_fao_fishing-12.0.1.0.1.dist-info/top_level.txt
odoo12_addon_product_fao_fishing-12.0.1.0.1.dist-info/RECORD
